{
	"info": {
		"_postman_id": "1a51d22c-da98-4e23-87f9-6721bf77bfc6",
		"name": "blockChain",
		"schema": "https://schema.getpostman.com/json/collection/v2.1.0/collection.json"
	},
	"item": [
		{
			"name": "balance",
			"request": {
				"method": "GET",
				"header": [],
				"url": {
					"raw": "http://localhost:1323/balance",
					"protocol": "http",
					"host": [
						"localhost"
					],
					"port": "1323",
					"path": [
						"balance"
					]
				}
			},
			"response": []
		},
		{
			"name": "admin",
			"request": {
				"method": "GET",
				"header": [],
				"url": {
					"raw": "http://localhost:1323/admin",
					"protocol": "http",
					"host": [
						"localhost"
					],
					"port": "1323",
					"path": [
						"admin"
					]
				}
			},
			"response": []
		},
		{
			"name": "deposite",
			"request": {
				"method": "POST",
				"header": [],
				"url": {
					"raw": "http://localhost:1323/deposite/100",
					"protocol": "http",
					"host": [
						"localhost"
					],
					"port": "1323",
					"path": [
						"deposite",
						"100"
					]
				}
			},
			"response": []
		},
		{
			"name": "withdrawl",
			"request": {
				"method": "POST",
				"header": [],
				"url": {
					"raw": "http://localhost:1323/withdrawl/100",
					"protocol": "http",
					"host": [
						"localhost"
					],
					"port": "1323",
					"path": [
						"withdrawl",
						"100"
					]
				}
			},
			"response": []
		}
	]
}